peacemakr
test
