Metadata-Version: 1.2
Name: peacemakr
Version: 0.0.2
Summary: Peacemakr
Home-page: UNKNOWN
Author-email: 
License: UNKNOWN
Keywords: Peacemakr
Platform: UNKNOWN
Classifier: Programming Language :: Python :: 3.6
Classifier: Programming Language :: Python :: 3.7
Classifier: Topic :: Security
Classifier: Topic :: Software Development :: Libraries
Requires-Python: >=3.6
